DuckDuck/__init__.py
DuckDuck/cache.py
DuckDuck/client.py
DuckDuck/http.py
DuckDuck/utils.py
DuckDuck-0.0.2.dist-info/LICENSE
DuckDuck-0.0.2.dist-info/METADATA
DuckDuck-0.0.2.dist-info/WHEEL
DuckDuck-0.0.2.dist-info/top_level.txt
DuckDuck-0.0.2.dist-info/RECORD
