Metadata-Version: 2.1
Name: DuckDuck
Version: 0.0.2
Summary: An async API wrapper for the Random-d.uk API
Home-page: https://github.com/iamSkev/duck
Author: iamSkev
Author-email: shawnkenzov@gmail.com
License: MIT
Keywords: duck,randomduck,randomduk,duckapi
Platform: UNKNOWN
Classifier: Development Status :: 1 - Planning
Classifier: License :: OSI Approved :: MIT License
Classifier: Programming Language :: Python :: 3.8
Classifier: Programming Language :: Python :: 3.9
Classifier: Topic :: Software Development :: Libraries
Classifier: Topic :: Software Development :: Libraries :: Python Modules
Requires-Dist: aiofiles (>=0.8.0)
Requires-Dist: aiohttp (>=3.8.1)
